README.md
setup.py
draham/__init__.py
draham/cli.py
draham/constants.py
draham/draham.py
draham/exceptions.py
draham/utils.py
draham.egg-info/PKG-INFO
draham.egg-info/SOURCES.txt
draham.egg-info/dependency_links.txt
draham.egg-info/entry_points.txt
draham.egg-info/requires.txt
draham.egg-info/top_level.txt