Metadata-Version: 2.1
Name: draham
Version: 1.0.0
Summary: A CLI crypto prices tracker.
Home-page: https://gitlab.com/fishrxyz/draham
Author: fishr (KC)
Author-email: fishr@fedora.email
License: UNKNOWN
Keywords: bitcoin ethereum crypto cryptocurrency cli tracker ticker
Platform: UNKNOWN
Classifier: Development Status :: 5 - Production/Stable
Classifier: Programming Language :: Python :: 3.9
Classifier: Intended Audience :: Developers
Requires-Python: >=3.7
